{
  "$id": "1",
  "AutoRefresh": true,
  "AutoRefreshRemotes": true,
  "CommitTextLinks": null,
  "DraftCommitMsg": "",
  "IncomingSavedCount": 0,
  "LastCheckedRemotes": "2023-03-03T18:40:27.9262702+01:00",
  "LastUsedView": 1,
  "LogBranchFilterIndex": 0,
  "OutgoingSavedCount": 0,
  "SidebarExpandedItems": [
    "File Status",
    "Branches",
    "File Status",
    "Branches",
    "File Status",
    "Branches",
    "File Status",
    "Branches",
    "File Status",
    "Branches",
    "File Status",
    "Branches",
    "Branches"
  ],
  "SidebarWidth": 210.0,
  "SubtreeLinks": [],
  "NeedsLargeFilesPull": false,
  "RemoteProjectLinks": []
}